MANIFEST.in
README.md
setup.py
colourlab/__init__.py
colourlab/data.py
colourlab/gamut.py
colourlab/image.py
colourlab/image_core.py
colourlab/metric.py
colourlab/misc.py
colourlab/space.py
colourlab/statistics.py
colourlab/tensor.py
colourlab.egg-info/PKG-INFO
colourlab.egg-info/SOURCES.txt
colourlab.egg-info/dependency_links.txt
colourlab.egg-info/requires.txt
colourlab.egg-info/top_level.txt
colourlab/colour_data/1929.dat
colourlab/colour_data/all.dat
colourlab/colour_data/ciexyz31_1.csv
colourlab/colour_data/ciexyz64_1.csv
colourlab/colour_data/readme.txt
colourlab/colour_data/real.dat
colourlab/metric_data/Data_RIT-DuPont.csv
colourlab/metric_data/Data_RIT-DuPont.xls
colourlab/metric_data/Mio_RIT_DuPont_Individual_Color_Difference_Data.csv
colourlab/metric_data/Mio_RIT_DuPont_Individual_Color_Difference_Data.xls
colourlab/tensor_data/3 observer.txt
colourlab/tensor_data/BFD (2).txt
colourlab/tensor_data/BFD_A.txt
colourlab/tensor_data/BFD_P.txt
colourlab/tensor_data/macdata(xyabtheta).mat
colourlab/tensor_data/noteBFD.txt