Metadata-Version: 1.0
Name: colourlab
Version: 0.0.3
Summary: Package for colour science and image processing
Home-page: https://github.com/ifarup/colourlab
Author: Ivar Farup et al.
Author-email: ivar.farup@ntnu.no
License: GPL3.0
Platform: UNKNOWN
